especifico/__init__.py
especifico/__main__.py
especifico/cli.py
especifico/exceptions.py
especifico/handlers.py
especifico/http_facts.py
especifico/json_schema.py
especifico/jsonifier.py
especifico/lifecycle.py
especifico/mock.py
especifico/options.py
especifico/problem.py
especifico/resolver.py
especifico/spec.py
especifico/utils.py
especifico/apis/__init__.py
especifico/apis/abstract.py
especifico/apis/aiohttp_api.py
especifico/apis/flask_api.py
especifico/apis/flask_utils.py
especifico/apps/__init__.py
especifico/apps/abstract.py
especifico/apps/aiohttp_app.py
especifico/apps/flask_app.py
especifico/decorators/__init__.py
especifico/decorators/coroutine_wrappers.py
especifico/decorators/decorator.py
especifico/decorators/metrics.py
especifico/decorators/parameter.py
especifico/decorators/produces.py
especifico/decorators/response.py
especifico/decorators/uri_parsing.py
especifico/decorators/validation.py
especifico/operations/__init__.py
especifico/operations/abstract.py
especifico/operations/compat.py
especifico/operations/openapi.py
especifico/operations/secure.py
especifico/operations/swagger2.py
especifico/resources/schemas/v2.0/schema.json
especifico/resources/schemas/v3.0/schema.json
especifico/security/__init__.py
especifico/security/aiohttp_security_handler_factory.py
especifico/security/async_security_handler_factory.py
especifico/security/flask_security_handler_factory.py
especifico/security/security_handler_factory.py
especifico-3.0.31.dist-info/LICENSE
especifico-3.0.31.dist-info/METADATA
especifico-3.0.31.dist-info/WHEEL
especifico-3.0.31.dist-info/entry_points.txt
especifico-3.0.31.dist-info/top_level.txt
especifico-3.0.31.dist-info/RECORD
