Metadata-Version: 2.1
Name: especifico
Version: 3.0.31
Summary: Específico - API first applications with OpenAPI/Swagger and Flask
Home-page: https://github.com/athenianco/especifico
Author: Zalando SE & Athenian
License: Apache License Version 2.0
Keywords: openapi oai swagger rest api oauth flask microservice framework
Platform: UNKNOWN
Classifier: Programming Language :: Python
Classifier: Programming Language :: Python :: 3.8
Classifier: Programming Language :: Python :: 3.9
Classifier: Programming Language :: Python :: 3.10
Classifier: Programming Language :: Python :: 3.11
Classifier: Development Status :: 5 - Production/Stable
Classifier: Intended Audience :: Developers
Classifier: Operating System :: OS Independent
Classifier: Topic :: Internet :: WWW/HTTP :: WSGI :: Application
Classifier: Topic :: Software Development :: Libraries :: Application Frameworks
Requires-Python: >=3.8
License-File: LICENSE
Requires-Dist: jsonschema (<5,>=4.0.1)
Requires-Dist: PyYAML (<7,>=5.1)
Requires-Dist: requests (<3,>=2.19.1)
Requires-Dist: inflection (<0.6,>=0.3.1)
Requires-Dist: werkzeug (<3,>=1.0)
Requires-Dist: packaging (>=20)
Requires-Dist: importlib-metadata (>=1) ; python_version < "3.8"
Provides-Extra: aiohttp
Requires-Dist: aiohttp (<4,>=2.3.10) ; extra == 'aiohttp'
Requires-Dist: aiohttp-jinja2 (<2,>=0.14.0) ; extra == 'aiohttp'
Requires-Dist: MarkupSafe (>=0.23) ; extra == 'aiohttp'
Provides-Extra: cli
Requires-Dist: clickclick (<21,>=1.2) ; extra == 'cli'
Provides-Extra: docs
Requires-Dist: sphinx-autoapi (==1.8.1) ; extra == 'docs'
Provides-Extra: flask
Requires-Dist: flask (<3,>=1.0.4) ; extra == 'flask'
Requires-Dist: itsdangerous (>=0.24) ; extra == 'flask'
Provides-Extra: swagger-ui
Requires-Dist: swagger-ui-bundle (<0.1,>=0.0.2) ; extra == 'swagger-ui'
Provides-Extra: tests
Requires-Dist: pytest-aiohttp (==1.0.4) ; extra == 'tests'
Requires-Dist: aiohttp-remotes (==1.2.0) ; extra == 'tests'
Requires-Dist: decorator (==5.1.1) ; extra == 'tests'
Requires-Dist: pytest (==7.2.2) ; extra == 'tests'
Requires-Dist: pytest-cov (==4.0.0) ; extra == 'tests'
Requires-Dist: testfixtures (==7.0.0) ; extra == 'tests'
